README.txt
TODO.txt
commands.py
dev.cfg
prod.cfg
sample-prod.cfg
setup.py
setup.pyc
start-mpd_webamp.py
MPD_WebAMP.egg-info/PKG-INFO
MPD_WebAMP.egg-info/SOURCES.txt
MPD_WebAMP.egg-info/dependency_links.txt
MPD_WebAMP.egg-info/entry_points.txt
MPD_WebAMP.egg-info/not-zip-safe
MPD_WebAMP.egg-info/requires.txt
MPD_WebAMP.egg-info/top_level.txt
mpd_webamp/COPYING.txt
mpd_webamp/README.txt
mpd_webamp/__init__.py
mpd_webamp/controllers.py
mpd_webamp/findlyrics.py
mpd_webamp/findlyrics_README.txt
mpd_webamp/i7AWF.py
mpd_webamp/json.py
mpd_webamp/model.py
mpd_webamp/mpdclient2.py
mpd_webamp/release.py
mpd_webamp/config/__init__.py
mpd_webamp/config/app.cfg
mpd_webamp/config/log.cfg
mpd_webamp/config/prod.cfg
mpd_webamp/static/images/favicon.ico
mpd_webamp/static/javascript/amp.js
mpd_webamp/static/javascript/async_receive.js
mpd_webamp/static/javascript/async_request.js
mpd_webamp/static/javascript/setup.js
mpd_webamp/static/themes/blue/style.css
mpd_webamp/static/themes/blue/style.css~
mpd_webamp/static/themes/default/Sort.png
mpd_webamp/static/themes/default/addall.png
mpd_webamp/static/themes/default/back.png
mpd_webamp/static/themes/default/button-back.png
mpd_webamp/static/themes/default/clickToPlay.png
mpd_webamp/static/themes/default/clickToRemove.png
mpd_webamp/static/themes/default/favicon.ico
mpd_webamp/static/themes/default/folder.png
mpd_webamp/static/themes/default/home.png
mpd_webamp/static/themes/default/insert.png
mpd_webamp/static/themes/default/media-playback-pause-high.png
mpd_webamp/static/themes/default/media-playback-pause-press.png
mpd_webamp/static/themes/default/media-playback-pause.png
mpd_webamp/static/themes/default/media-playback-start-high.png
mpd_webamp/static/themes/default/media-playback-start-press.png
mpd_webamp/static/themes/default/media-playback-start.png
mpd_webamp/static/themes/default/media-playback-stop-high.png
mpd_webamp/static/themes/default/media-playback-stop-press.png
mpd_webamp/static/themes/default/media-playback-stop.png
mpd_webamp/static/themes/default/media-seek-backward-high.png
mpd_webamp/static/themes/default/media-seek-backward-press.png
mpd_webamp/static/themes/default/media-seek-backward.png
