Metadata-Version: 1.0
Name: MPD-WebAMP
Version: 1.1
Summary: MPD WebAMP is an asynchronous web client for the Music Player Daemon
Home-page: http://cseickel.googlepages.com/mpdwebamp
Author: cseickel
Author-email: cseickel at gmail dot com
License: GPL 2
Keywords: mpd client,music,lyrics,lastfm,album art,turbogears.app
Platform: UNKNOWN
Classifier: Operating System :: OS Independent
Classifier: Programming Language :: Python
Classifier: Framework :: TurboGears
Classifier: Framework :: TurboGears :: Applications
Classifier: Topic :: Multimedia :: Sound/Audio :: Players
Classifier: Topic :: Internet :: WWW/HTTP :: HTTP Servers
Classifier: Intended Audience :: End Users/Desktop
Classifier: License :: OSI Approved :: GNU General Public License (GPL)
